ddu_dirty_mnist/__init__.py
ddu_dirty_mnist/_nbdev.py
ddu_dirty_mnist/core.py
ddu_dirty_mnist/dirty_mnist.py
ddu_dirty_mnist-1.1.1.dist-info/LICENSE
ddu_dirty_mnist-1.1.1.dist-info/METADATA
ddu_dirty_mnist-1.1.1.dist-info/WHEEL
ddu_dirty_mnist-1.1.1.dist-info/entry_points.txt
ddu_dirty_mnist-1.1.1.dist-info/top_level.txt
ddu_dirty_mnist-1.1.1.dist-info/RECORD
