Metadata-Version: 2.1
Name: ddu-dirty-mnist
Version: 1.1.1
Summary: Dirty-MNIST from "Deterministic Neural Networks with Appropriate Inductive Biases Capture Epistemic and Aleatoric Uncertainty"
Home-page: https://github.com/blackhc/ddu_dirty_mnist/tree/master/
Author: Jishnu Mukhoti, Andreas Kirsch, Joost van Amersfoort, Philip H.S. Torr, Yarin Gal
Author-email: blackhc+ddu_dirty_mnist@gmail.com
License: Apache Software License 2.0
Keywords: torch,dirtymnist,ddu,machine learning
Platform: UNKNOWN
Classifier: Development Status :: 5 - Production/Stable
Classifier: Intended Audience :: Developers
Classifier: Natural Language :: English
Classifier: Programming Language :: Python :: 3.7
Classifier: Programming Language :: Python :: 3.8
Classifier: License :: OSI Approved :: Apache Software License
Requires-Python: >=3.7
Requires-Dist: torch
Requires-Dist: torchvision
Requires-Dist: tqdm
Provides-Extra: dev
Requires-Dist: pytorch ; extra == 'dev'
Requires-Dist: torchvision ; extra == 'dev'
Requires-Dist: matplotlib ; extra == 'dev'
Requires-Dist: seaborn ; extra == 'dev'
Requires-Dist: numpy ; extra == 'dev'
Requires-Dist: tqdm ; extra == 'dev'
